odoo/addons/product_net_weight/README.rst
odoo/addons/product_net_weight/__init__.py
odoo/addons/product_net_weight/__manifest__.py
odoo/addons/product_net_weight/demo/product_product.xml
odoo/addons/product_net_weight/i18n/es.po
odoo/addons/product_net_weight/i18n/fr.po
odoo/addons/product_net_weight/i18n/it.po
odoo/addons/product_net_weight/i18n/product_net_weight.pot
odoo/addons/product_net_weight/models/__init__.py
odoo/addons/product_net_weight/models/product_product.py
odoo/addons/product_net_weight/models/product_template.py
odoo/addons/product_net_weight/readme/CONTRIBUTORS.md
odoo/addons/product_net_weight/readme/DESCRIPTION.md
odoo/addons/product_net_weight/readme/ROADMAP.md
odoo/addons/product_net_weight/readme/USAGE.md
odoo/addons/product_net_weight/static/description/icon.png
odoo/addons/product_net_weight/static/description/index.html
odoo/addons/product_net_weight/static/description/product_form.png
odoo/addons/product_net_weight/tests/__init__.py
odoo/addons/product_net_weight/tests/test_product_net_weight.py
odoo/addons/product_net_weight/views/view_product_product.xml
odoo/addons/product_net_weight/views/view_product_template.xml
odoo_addon_product_net_weight-19.0.1.0.1.dist-info/METADATA
odoo_addon_product_net_weight-19.0.1.0.1.dist-info/WHEEL
odoo_addon_product_net_weight-19.0.1.0.1.dist-info/top_level.txt
odoo_addon_product_net_weight-19.0.1.0.1.dist-info/RECORD
