Metadata-Version: 2.1
Name: odoo-addon-product_net_weight
Version: 19.0.1.0.1
Requires-Dist: odoo==19.0.*
Summary: Add 'Net Weight' on product models
Home-page: https://github.com/OCA/product-attribute
License: AGPL-3
Author: GRAP,Odoo Community Association (OCA)
Author-email: support@odoo-community.org
Classifier: Programming Language :: Python
Classifier: Framework :: Odoo
Classifier: Framework :: Odoo :: 19.0
Classifier: License :: OSI Approved :: GNU Affero General Public License v3
